zortheix/__init__.py
zortheix/run.bat
zortheix/jdevtools/__init__.py
zortheix/jdevtools/jCLI.py
zortheix/jdevtools/jgui.py
zortheix/jdevtools/jweb.py
zortheix/jdevtools/bots/__init__.py
zortheix/jdevtools/data/__init__.py
zortheix/jdevtools/extras/__init__.py
zortheix/jdevtools/models/__init__.py
zortheix/jdevtools/models/jkanda.py
zortheix/jdevtools/models/jkissalu.py
zortheix/jdevtools/models/jmesso.py
zortheix/jdevtools/servers/__init__.py
zortheix-0.0.0.0.dist-info/LICENSE
zortheix-0.0.0.0.dist-info/WHEEL
zortheix-0.0.0.0.dist-info/METADATA
zortheix-0.0.0.0.dist-info/RECORD
