Metadata-Version: 2.1
Name: zortheix
Version: 0.0.0.0
Summary: 👨‍💻🛠️⌛📦Zortheix, when diverse cross technologies meet to offer the best !🔥...🏃
Author: Juste Elysée MALANDILA (jdevseer)
Author-email: malandilajusteelysee@gmail.com
Classifier: License :: OSI Approved :: GNU General Public License v3 or later (GPLv3+)
Classifier: Programming Language :: Python :: 2
Classifier: Programming Language :: Python :: 3
Classifier: License :: OSI Approved :: GNU General Public License v3 (GPLv3)
